seq101.v
module seq101(
    input clk,
    input rst,
    input x,
    output reg y
);

reg [1:0]state;

always@(posedge clk or posedge rst)
begin
    if (rst)begin
        state<=2'b00;
        y<=1'b0;
end
else begin
case (state)
2'b00:  begin
    y<=1'b0;
    if (x)  
        state<=2'b01;
        else 
        state<=2'b00;
end
2'b01: begin 
    y<=1'b0;
    if (x)
    state<=2'b01;
    else
    state<=2'b10;
end
2'b10: begin
    if (x) begin
    y<=1'b1;
    state<=2'b00; end
    else begin
    y<=1'b0;
    state<=2'b00; end
end
default: begin
    state<=2'b00;
    y<=1'b0;
end
endcase 
end
end
endmodule

tb_seq101.v
`timescale 1ns/1ps

module tb_seq101;
reg clk;
reg rst;
reg x;
wire y;

seq101 uut(
    .clk(clk),
    .rst(rst),
    .x(x),
    .y(y)
);
initial begin
    $dumpfile("seq101.vcd");
    $dumpvars(0, tb_seq101);
end

always #5 clk=~clk;
initial begin
    clk =0;
    rst=1;
    x=0;
    #10;
    rst=0;
    x = 1; #10;
    x = 0; #10;
    x = 1; #10;

    x = 1; #10;
    x = 1; #10;
    x = 0; #10;
    x = 1; #10;
    #20;
    $finish;


end

    
endmodule

seq101.vcd
$date
	Tue Jun  9 12:51:00 2026
$end
$version
	Icarus Verilog
$end
$timescale
	1ps
$end
$scope module tb_seq101 $end
$var wire 1 ! y $end
$var reg 1 " clk $end
$var reg 1 # rst $end
$var reg 1 $ x $end
$scope module uut $end
$var wire 1 " clk $end
$var wire 1 # rst $end
$var wire 1 $ x $end
$var reg 2 % state [1:0] $end
$var reg 1 ! y $end
$upscope $end
$upscope $end
$enddefinitions $end
$comment Show the parameter values. $end
$dumpall
$end
#0
$dumpvars
b0 %
0$
1#
0"
0!
$end
#5000
1"
#10000
0"
1$
0#
#15000
b1 %
1"
#20000
0"
0$
#25000
b10 %
1"
#30000
0"
1$
#35000
b0 %
1!
1"
#40000
0"
#45000
b1 %
0!
1"
#50000
0"
#55000
1"
#60000
0"
0$
#65000
b10 %
1"
#70000
0"
1$
#75000
b0 %
1!
1"
#80000
0"
#85000
b1 %
0!
1"
